{"cameraMode":{"drawMode":0,"name":"Shaded","section":"Shading Mode"},"sceneLighting":true,"audioPlay":false,"sceneViewState":{"m_AlwaysRefresh":false,"showFog":true,"showSkybox":true,"showFlares":true,"showImageEffects":true,"showParticleSystems":true,"showVisualEffectGraphs":true,"m_FxEnabled":true},"in2DMode":false,"pivot":{"x":-0.38207530975341799,"y":2.7712764739990236,"z":-5.6587114334106449},"rotation":{"x":0.09482010453939438,"y":0.2380119115114212,"z":-0.023354547098279,"w":0.9663435816764832},"size":4.042355537414551,"orthographic":false}